LICENSE
MANIFEST.in
README.rst
setup.py
workfront/__init__.py
workfront/exceptions.py
workfront/workfront.py
workfront/workfront_subs.py
workfront/objects/__init__.py
workfront/objects/codes.py
workfront/objects/custom_form.py
workfront/objects/fields.py
workfront/objects/generic_object_param_value.py
workfront/objects/generic_objects.py
workfront/objects/parameter.py
workfront/objects/portfolio.py
workfront/objects/program.py
workfront/objects/project.py
workfront/objects/status.py
workfront/objects/task.py
workfront/objects/template_project.py
workfront/objects/template_task.py
workfront/objects/user.py
workfront_sdk.egg-info/PKG-INFO
workfront_sdk.egg-info/SOURCES.txt
workfront_sdk.egg-info/dependency_links.txt
workfront_sdk.egg-info/not-zip-safe
workfront_sdk.egg-info/requires.txt
workfront_sdk.egg-info/top_level.txt