Metadata-Version: 2.1
Name: workfront-sdk
Version: 0.25
Summary: Workfront for Python (SDK)
Home-page: https://github.com/BridgeMarketing/workfront-sdk
Author: Bridge
Author-email: info@bridgecorp.com
License: GPL
Platform: UNKNOWN
License-File: LICENSE
